mope/__init__.py
mope/__version__.py
mope/client.py
mope/models/__init__.py
mope/models/payments.py
mope/resources/__init__.py
mope/resources/shop.py
python_mope-0.1.0.dist-info/METADATA
python_mope-0.1.0.dist-info/WHEEL
python_mope-0.1.0.dist-info/top_level.txt
python_mope-0.1.0.dist-info/zip-safe
python_mope-0.1.0.dist-info/RECORD
