Metadata-Version: 2.1
Name: python-mope
Version: 0.1.0
Summary: A client library for interacting with the Mopé Web Shop API
Home-page: https://github.com/rhymiz/python-mope
Author: Lemuel Boyce
Author-email: lemuel@vokality.com
License: MIT
Classifier: Programming Language :: Python :: 3
Classifier: Programming Language :: Python :: 3.7
Classifier: Programming Language :: Python :: 3.8
Classifier: Programming Language :: Python :: 3.9
Classifier: Programming Language :: Python :: 3.10
Classifier: Programming Language :: Python :: 3.11
Classifier: License :: OSI Approved :: MIT License
Classifier: Operating System :: OS Independent
Classifier: Development Status :: 6 - Mature
Classifier: Environment :: Web Environment
Classifier: Intended Audience :: Developers
Classifier: Topic :: Office/Business :: Financial
Classifier: Topic :: Software Development :: Libraries :: Python Modules
Requires-Python: >=3.7,<=3.11
Requires-Dist: requests (>=2.23.0)
